{
  "final_energy": -58.87946474724951,
  "n_dets": 200,
  "config": {
    "threshold": 0.03,
    "local_trim_keep_ratio": 0.1,
    "verbose": false,
    "initial_pool_size": 100,
    "core_set_ratio": 1.02,
    "pool_core_ratio": 20,
    "max_final_dets": 200,
    "max_rounds": 2,
    "pool_build_strategy": "heat_bath",
    "num_groups": 10,
    "load_initial_dets": false,
    "num_runs": 1,
    "first_cycle_keep_size": 10,
    "psym": 8,
    "fcidump_path": "/tmp/tmprrbpnkz4.fcidump",
    "nuclear_repulsion": 0.0
  },
  "iteration_summary": {
    "iterations": [
      {
        "iteration": 1,
        "core_set_size_before": 1,
        "target_pool_size": 100,
        "actual_pool_size": 140,
        "final_threshold": 0.03,
        "pool_building_time": 0.0001881,
        "trim_m": 10,
        "trim_k": 1,
        "raw_dets_count": 11,
        "raw_energy": -57.371248717931806,
        "energy_change": 0.0,
        "converged": false,
        "core_set_size_after": 10,
        "iteration_time": 0.000758633,
        "cumulative_time": 0.003550158
      },
      {
        "iteration": 2,
        "core_set_size_before": 10,
        "target_pool_size": 200,
        "actual_pool_size": 205,
        "final_threshold": 0.012914016300000003,
        "pool_building_time": 0.001072683,
        "trim_m": 10,
        "trim_k": 1,
        "raw_dets_count": 20,
        "raw_energy": -57.80489553586443,
        "energy_change": -0.43364681793262605,
        "converged": false,
        "core_set_size_after": 11,
        "iteration_time": 0.00197945,
        "cumulative_time": 0.005534191
      },
      {
        "iteration": 3,
        "core_set_size_before": 11,
        "target_pool_size": 220,
        "actual_pool_size": 497,
        "final_threshold": 0.012914016300000003,
        "pool_building_time": 0.000408925,
        "trim_m": 10,
        "trim_k": 1,
        "raw_dets_count": 21,
        "raw_energy": -57.98630338010628,
        "energy_change": -0.1814078442418463,
        "converged": false,
        "core_set_size_after": 12,
        "iteration_time": 0.001710041,
        "cumulative_time": 0.007248999
      },
      {
        "iteration": 4,
        "core_set_size_before": 12,
        "target_pool_size": 240,
        "actual_pool_size": 510,
        "final_threshold": 0.012914016300000003,
        "pool_building_time": 0.000427258,
        "trim_m": 10,
        "trim_k": 1,
        "raw_dets_count": 22,
        "raw_energy": -58.39787052478746,
        "energy_change": -0.41156714468117883,
        "converged": false,
        "core_set_size_after": 13,
        "iteration_time": 0.005980882,
        "cumulative_time": 0.013234556
      },
      {
        "iteration": 5,
        "core_set_size_before": 13,
        "target_pool_size": 260,
        "actual_pool_size": 485,
        "final_threshold": 0.012914016300000003,
        "pool_building_time": 0.001821599,
        "trim_m": 10,
        "trim_k": 1,
        "raw_dets_count": 23,
        "raw_energy": -58.6159192229818,
        "energy_change": -0.21804869819434458,
        "converged": false,
        "core_set_size_after": 14,
        "iteration_time": 0.003294133,
        "cumulative_time": 0.016533914
      },
      {
        "iteration": 6,
        "core_set_size_before": 14,
        "target_pool_size": 280,
        "actual_pool_size": 373,
        "final_threshold": 0.011622614670000003,
        "pool_building_time": 0.000445683,
        "trim_m": 10,
        "trim_k": 1,
        "raw_dets_count": 24,
        "raw_energy": -58.76609966861952,
        "energy_change": -0.15018044563771582,
        "converged": false,
        "core_set_size_after": 15,
        "iteration_time": 0.001805741,
        "cumulative_time": 0.018351572
      },
      {
        "iteration": 7,
        "core_set_size_before": 15,
        "target_pool_size": 300,
        "actual_pool_size": 360,
        "final_threshold": 0.009414317882700002,
        "pool_building_time": 0.000571358,
        "trim_m": 10,
        "trim_k": 1,
        "raw_dets_count": 25,
        "raw_energy": -58.77280206389222,
        "energy_change": -0.006702395272704109,
        "converged": false,
        "core_set_size_after": 16,
        "iteration_time": 0.017928713,
        "cumulative_time": 0.036285327
      },
      {
        "iteration": 8,
        "core_set_size_before": 16,
        "target_pool_size": 320,
        "actual_pool_size": 391,
        "final_threshold": 0.009414317882700002,
        "pool_building_time": 0.000515258,
        "trim_m": 10,
        "trim_k": 1,
        "raw_dets_count": 26,
        "raw_energy": -58.78133636517512,
        "energy_change": -0.008534301282900003,
        "converged": false,
        "core_set_size_after": 17,
        "iteration_time": 0.002065708,
        "cumulative_time": 0.038356902
      },
      {
        "iteration": 9,
        "core_set_size_before": 17,
        "target_pool_size": 340,
        "actual_pool_size": 411,
        "final_threshold": 0.008472886094430003,
        "pool_building_time": 0.00064295,
        "trim_m": 10,
        "trim_k": 1,
        "raw_dets_count": 27,
        "raw_energy": -58.7856961435425,
        "energy_change": -0.004359778367380329,
        "converged": false,
        "core_set_size_after": 18,
        "iteration_time": 0.008699257,
        "cumulative_time": 0.047062025
      },
      {
        "iteration": 10,
        "core_set_size_before": 18,
        "target_pool_size": 360,
        "actual_pool_size": 388,
        "final_threshold": 0.008472886094430003,
        "pool_building_time": 0.000500225,
        "trim_m": 10,
        "trim_k": 1,
        "raw_dets_count": 28,
        "raw_energy": -58.7874092397008,
        "energy_change": -0.0017130961582978443,
        "converged": false,
        "core_set_size_after": 19,
        "iteration_time": 0.002004475,
        "cumulative_time": 0.04907585
      },
      {
        "iteration": 11,
        "core_set_size_before": 19,
        "target_pool_size": 380,
        "actual_pool_size": 443,
        "final_threshold": 0.008472886094430003,
        "pool_building_time": 0.000475291,
        "trim_m": 10,
        "trim_k": 1,
        "raw_dets_count": 29,
        "raw_energy": -58.7890220812317,
        "energy_change": -0.0016128415308998,
        "converged": false,
        "core_set_size_after": 20,
        "iteration_time": 0.008379432,
        "cumulative_time": 0.057461148
      },
      {
        "iteration": 12,
        "core_set_size_before": 20,
        "target_pool_size": 400,
        "actual_pool_size": 425,
        "final_threshold": 0.008472886094430003,
        "pool_building_time": 0.001383708,
        "trim_m": 10,
        "trim_k": 1,
        "raw_dets_count": 30,
        "raw_energy": -58.79369834060876,
        "energy_change": -0.0046762593770637295,
        "converged": false,
        "core_set_size_after": 21,
        "iteration_time": 0.009598873,
        "cumulative_time": 0.067067721
      },
      {
        "iteration": 13,
        "core_set_size_before": 21,
        "target_pool_size": 420,
        "actual_pool_size": 426,
        "final_threshold": 0.006863037736488302,
        "pool_building_time": 0.000772016,
        "trim_m": 10,
        "trim_k": 1,
        "raw_dets_count": 31,
        "raw_energy": -58.79361380135803,
        "energy_change": 8.453925073581559e-05,
        "converged": false,
        "core_set_size_after": 22,
        "iteration_time": 0.002415966,
        "cumulative_time": 0.069489554
      },
      {
        "iteration": 14,
        "core_set_size_before": 22,
        "target_pool_size": 440,
        "actual_pool_size": 706,
        "final_threshold": 0.006863037736488302,
        "pool_building_time": 0.000773117,
        "trim_m": 10,
        "trim_k": 1,
        "raw_dets_count": 32,
        "raw_energy": -58.79846814444453,
        "energy_change": -0.0048543430864995685,
        "converged": false,
        "core_set_size_after": 23,
        "iteration_time": 0.029919352,
        "cumulative_time": 0.099414315
      },
      {
        "iteration": 15,
        "core_set_size_before": 23,
        "target_pool_size": 460,
        "actual_pool_size": 745,
        "final_threshold": 0.006863037736488302,
        "pool_building_time": 0.005068432,
        "trim_m": 10,
        "trim_k": 1,
        "raw_dets_count": 33,
        "raw_energy": -58.79931977526368,
        "energy_change": -0.0008516308191559574,
        "converged": false,
        "core_set_size_after": 24,
        "iteration_time": 0.014760073,
        "cumulative_time": 0.114181263
      },
      {
        "iteration": 16,
        "core_set_size_before": 24,
        "target_pool_size": 480,
        "actual_pool_size": 751,
        "final_threshold": 0.006863037736488302,
        "pool_building_time": 0.000833066,
        "trim_m": 10,
        "trim_k": 1,
        "raw_dets_count": 34,
        "raw_energy": -58.79886869067474,
        "energy_change": 0.000451084588945605,
        "converged": false,
        "core_set_size_after": 25,
        "iteration_time": 0.003090266,
        "cumulative_time": 0.117277945
      },
      {
        "iteration": 17,
        "core_set_size_before": 25,
        "target_pool_size": 500,
        "actual_pool_size": 726,
        "final_threshold": 0.006863037736488302,
        "pool_building_time": 0.000789891,
        "trim_m": 10,
        "trim_k": 1,
        "raw_dets_count": 35,
        "raw_energy": -58.79968902456311,
        "energy_change": -0.0008203338883703282,
        "converged": false,
        "core_set_size_after": 26,
        "iteration_time": 0.00431255,
        "cumulative_time": 0.121596545
      },
      {
        "iteration": 18,
        "core_set_size_before": 26,
        "target_pool_size": 520,
        "actual_pool_size": 692,
        "final_threshold": 0.006863037736488302,
        "pool_building_time": 0.004048916,
        "trim_m": 10,
        "trim_k": 1,
        "raw_dets_count": 36,
        "raw_energy": -58.80051018238581,
        "energy_change": -0.0008211578226990923,
        "converged": false,
        "core_set_size_after": 27,
        "iteration_time": 0.012791623,
        "cumulative_time": 0.134398526
      },
      {
        "iteration": 19,
        "core_set_size_before": 27,
        "target_pool_size": 540,
        "actual_pool_size": 631,
        "final_threshold": 0.006863037736488302,
        "pool_building_time": 0.000756524,
        "trim_m": 10,
        "trim_k": 1,
        "raw_dets_count": 37,
        "raw_energy": -58.80056797640612,
        "energy_change": -5.7794020314361205e-05,
        "converged": false,
        "core_set_size_after": 28,
        "iteration_time": 0.008667357,
        "cumulative_time": 0.143072391
      },
      {
        "iteration": 20,
        "core_set_size_before": 28,
        "target_pool_size": 560,
        "actual_pool_size": 602,
        "final_threshold": 0.006863037736488302,
        "pool_building_time": 0.002186983,
        "trim_m": 10,
        "trim_k": 1,
        "raw_dets_count": 38,
        "raw_energy": -58.801860458874735,
        "energy_change": -0.0012924824686137981,
        "converged": false,
        "core_set_size_after": 29,
        "iteration_time": 0.004580307,
        "cumulative_time": 0.147659848
      },
      {
        "iteration": 21,
        "core_set_size_before": 29,
        "target_pool_size": 580,
        "actual_pool_size": 610,
        "final_threshold": 0.006863037736488302,
        "pool_building_time": 0.000774125,
        "trim_m": 10,
        "trim_k": 1,
        "raw_dets_count": 39,
        "raw_energy": -58.802600368343604,
        "energy_change": -0.0007399094688693708,
        "converged": false,
        "core_set_size_after": 30,
        "iteration_time": 0.003169742,
        "cumulative_time": 0.150868273
      },
      {
        "iteration": 22,
        "core_set_size_before": 30,
        "target_pool_size": 600,
        "actual_pool_size": 716,
        "final_threshold": 0.0061767339628394724,
        "pool_building_time": 0.001081667,
        "trim_m": 10,
        "trim_k": 1,
        "raw_dets_count": 40,
        "raw_energy": -58.803482720883906,
        "energy_change": -0.0008823525403016674,
        "converged": false,
        "core_set_size_after": 31,
        "iteration_time": 0.003865857,
        "cumulative_time": 0.15477373
      },
      {
        "iteration": 23,
        "core_set_size_before": 31,
        "target_pool_size": 620,
        "actual_pool_size": 840,
        "final_threshold": 0.0061767339628394724,
        "pool_building_time": 0.000959475,
        "trim_m": 10,
        "trim_k": 1,
        "raw_dets_count": 41,
        "raw_energy": -58.803643264858856,
        "energy_change": -0.00016054397494968953,
        "converged": false,
        "core_set_size_after": 32,
        "iteration_time": 0.009052173,
        "cumulative_time": 0.16386532
      },
      {
        "iteration": 24,
        "core_set_size_before": 32,
        "target_pool_size": 640,
        "actual_pool_size": 839,
        "final_threshold": 0.0061767339628394724,
        "pool_building_time": 0.001037392,
        "trim_m": 10,
        "trim_k": 1,
        "raw_dets_count": 42,
        "raw_energy": -58.80370695141306,
        "energy_change": -6.36865542062992e-05,
        "converged": false,
        "core_set_size_after": 33,
        "iteration_time": 0.012920597,
        "cumulative_time": 0.176831659
      },
      {
        "iteration": 25,
        "core_set_size_before": 33,
        "target_pool_size": 660,
        "actual_pool_size": 810,
        "final_threshold": 0.0061767339628394724,
        "pool_building_time": 0.015691498,
        "trim_m": 10,
        "trim_k": 1,
        "raw_dets_count": 43,
        "raw_energy": -58.80383620454555,
        "energy_change": -0.0001292531324850188,
        "converged": false,
        "core_set_size_after": 34,
        "iteration_time": 0.041483009,
        "cumulative_time": 0.218359585
      },
      {
        "iteration": 26,
        "core_set_size_before": 34,
        "target_pool_size": 680,
        "actual_pool_size": 814,
        "final_threshold": 0.0061767339628394724,
        "pool_building_time": 0.000858916,
        "trim_m": 10,
        "trim_k": 1,
        "raw_dets_count": 44,
        "raw_energy": -58.80515536556116,
        "energy_change": -0.0013191610156155775,
        "converged": false,
        "core_set_size_after": 35,
        "iteration_time": 0.003654291,
        "cumulative_time": 0.222020751
      },
      {
        "iteration": 27,
        "core_set_size_before": 35,
        "target_pool_size": 700,
        "actual_pool_size": 795,
        "final_threshold": 0.0061767339628394724,
        "pool_building_time": 0.000884583,
        "trim_m": 10,
        "trim_k": 1,
        "raw_dets_count": 45,
        "raw_energy": -58.80752347269411,
        "energy_change": -0.0023681071329448855,
        "converged": false,
        "core_set_size_after": 36,
        "iteration_time": 0.019502355,
        "cumulative_time": 0.241529523
      },
      {
        "iteration": 28,
        "core_set_size_before": 36,
        "target_pool_size": 720,
        "actual_pool_size": 783,
        "final_threshold": 0.0061767339628394724,
        "pool_building_time": 0.006508332,
        "trim_m": 10,
        "trim_k": 1,
        "raw_dets_count": 46,
        "raw_energy": -58.80653406262618,
        "energy_change": 0.0009894100679304074,
        "converged": false,
        "core_set_size_after": 37,
        "iteration_time": 0.010091214,
        "cumulative_time": 0.251628712
      },
      {
        "iteration": 29,
        "core_set_size_before": 37,
        "target_pool_size": 740,
        "actual_pool_size": 789,
        "final_threshold": 0.0061767339628394724,
        "pool_building_time": 0.000798141,
        "trim_m": 10,
        "trim_k": 1,
        "raw_dets_count": 47,
        "raw_energy": -58.80728601901124,
        "energy_change": -0.0007519563850593158,
        "converged": false,
        "core_set_size_after": 38,
        "iteration_time": 0.007314999,
        "cumulative_time": 0.258949211
      },
      {
        "iteration": 30,
        "core_set_size_before": 38,
        "target_pool_size": 760,
        "actual_pool_size": 934,
        "final_threshold": 0.005559060566555525,
        "pool_building_time": 0.006640515,
        "trim_m": 10,
        "trim_k": 1,
        "raw_dets_count": 48,
        "raw_energy": -58.80679364187732,
        "energy_change": 0.0004923771339164773,
        "converged": false,
        "core_set_size_after": 39,
        "iteration_time": 0.027678103,
        "cumulative_time": 0.286633364
      },
      {
        "iteration": 31,
        "core_set_size_before": 39,
        "target_pool_size": 780,
        "actual_pool_size": 1179,
        "final_threshold": 0.005559060566555525,
        "pool_building_time": 0.001396633,
        "trim_m": 10,
        "trim_k": 1,
        "raw_dets_count": 49,
        "raw_energy": -58.80666525802513,
        "energy_change": 0.000128383852192826,
        "converged": false,
        "core_set_size_after": 40,
        "iteration_time": 0.006640424,
        "cumulative_time": 0.293317055
      },
      {
        "iteration": 32,
        "core_set_size_before": 40,
        "target_pool_size": 800,
        "actual_pool_size": 1167,
        "final_threshold": 0.005559060566555525,
        "pool_building_time": 0.001294242,
        "trim_m": 10,
        "trim_k": 1,
        "raw_dets_count": 50,
        "raw_energy": -58.80717495397598,
        "energy_change": -0.0005096959508534837,
        "converged": false,
        "core_set_size_after": 41,
        "iteration_time": 0.018846572,
        "cumulative_time": 0.312206435
      },
      {
        "iteration": 33,
        "core_set_size_before": 41,
        "target_pool_size": 820,
        "actual_pool_size": 1136,
        "final_threshold": 0.005559060566555525,
        "pool_building_time": 0.001319541,
        "trim_m": 10,
        "trim_k": 1,
        "raw_dets_count": 51,
        "raw_energy": -58.80932803270496,
        "energy_change": -0.0021530787289805176,
        "converged": false,
        "core_set_size_after": 42,
        "iteration_time": 0.005413374,
        "cumulative_time": 0.317666742
      },
      {
        "iteration": 34,
        "core_set_size_before": 42,
        "target_pool_size": 840,
        "actual_pool_size": 1129,
        "final_threshold": 0.005559060566555525,
        "pool_building_time": 0.001164899,
        "trim_m": 10,
        "trim_k": 1,
        "raw_dets_count": 52,
        "raw_energy": -58.81757943669374,
        "energy_change": -0.00825140398877977,
        "converged": false,
        "core_set_size_after": 43,
        "iteration_time": 0.012451906,
        "cumulative_time": 0.330167873
      },
      {
        "iteration": 35,
        "core_set_size_before": 43,
        "target_pool_size": 860,
        "actual_pool_size": 1447,
        "final_threshold": 0.005559060566555525,
        "pool_building_time": 0.001470883,
        "trim_m": 10,
        "trim_k": 1,
        "raw_dets_count": 53,
        "raw_energy": -58.832706855221375,
        "energy_change": -0.015127418527633552,
        "converged": false,
        "core_set_size_after": 44,
        "iteration_time": 0.116198754,
        "cumulative_time": 0.446412002
      },
      {
        "iteration": 36,
        "core_set_size_before": 44,
        "target_pool_size": 880,
        "actual_pool_size": 1383,
        "final_threshold": 0.005559060566555525,
        "pool_building_time": 0.013209439,
        "trim_m": 10,
        "trim_k": 1,
        "raw_dets_count": 54,
        "raw_energy": -58.835856356030845,
        "energy_change": -0.003149500809470851,
        "converged": false,
        "core_set_size_after": 45,
        "iteration_time": 0.048626316,
        "cumulative_time": 0.495085618
      },
      {
        "iteration": 37,
        "core_set_size_before": 45,
        "target_pool_size": 900,
        "actual_pool_size": 1339,
        "final_threshold": 0.005559060566555525,
        "pool_building_time": 0.00133815,
        "trim_m": 10,
        "trim_k": 1,
        "raw_dets_count": 55,
        "raw_energy": -58.837016299074314,
        "energy_change": -0.0011599430434685587,
        "converged": false,
        "core_set_size_after": 46,
        "iteration_time": 0.00955194,
        "cumulative_time": 0.504680366
      },
      {
        "iteration": 38,
        "core_set_size_before": 46,
        "target_pool_size": 920,
        "actual_pool_size": 1281,
        "final_threshold": 0.005559060566555525,
        "pool_building_time": 0.003694716,
        "trim_m": 10,
        "trim_k": 1,
        "raw_dets_count": 56,
        "raw_energy": -58.839019736547584,
        "energy_change": -0.002003437473270253,
        "converged": false,
        "core_set_size_after": 47,
        "iteration_time": 0.015528055,
        "cumulative_time": 0.520265346
      },
      {
        "iteration": 39,
        "core_set_size_before": 47,
        "target_pool_size": 940,
        "actual_pool_size": 1189,
        "final_threshold": 0.005559060566555525,
        "pool_building_time": 0.001237225,
        "trim_m": 10,
        "trim_k": 1,
        "raw_dets_count": 57,
        "raw_energy": -58.84375772700807,
        "energy_change": -0.004737990460483843,
        "converged": false,
        "core_set_size_after": 48,
        "iteration_time": 0.01139939,
        "cumulative_time": 0.531716436
      },
      {
        "iteration": 40,
        "core_set_size_before": 48,
        "target_pool_size": 960,
        "actual_pool_size": 1077,
        "final_threshold": 0.005559060566555525,
        "pool_building_time": 0.00825174,
        "trim_m": 10,
        "trim_k": 1,
        "raw_dets_count": 58,
        "raw_energy": -58.84753753178333,
        "energy_change": -0.0037798047752630737,
        "converged": false,
        "core_set_size_after": 49,
        "iteration_time": 0.037808185,
        "cumulative_time": 0.569531404
      },
      {
        "iteration": 41,
        "core_set_size_before": 49,
        "target_pool_size": 980,
        "actual_pool_size": 1001,
        "final_threshold": 0.005559060566555525,
        "pool_building_time": 0.004879049,
        "trim_m": 10,
        "trim_k": 1,
        "raw_dets_count": 59,
        "raw_energy": -58.85011410658264,
        "energy_change": -0.002576574799306286,
        "converged": false,
        "core_set_size_after": 50,
        "iteration_time": 0.017606138,
        "cumulative_time": 0.587183467
      },
      {
        "iteration": 42,
        "core_set_size_before": 50,
        "target_pool_size": 1000,
        "actual_pool_size": 1093,
        "final_threshold": 0.005003154509899972,
        "pool_building_time": 0.001368491,
        "trim_m": 10,
        "trim_k": 1,
        "raw_dets_count": 60,
        "raw_energy": -58.851411364057995,
        "energy_change": -0.0012972574753575827,
        "converged": false,
        "core_set_size_after": 51,
        "iteration_time": 0.005748966,
        "cumulative_time": 0.592975975
      },
      {
        "iteration": 43,
        "core_set_size_before": 51,
        "target_pool_size": 1020,
        "actual_pool_size": 1173,
        "final_threshold": 0.005003154509899972,
        "pool_building_time": 0.001405983,
        "trim_m": 10,
        "trim_k": 1,
        "raw_dets_count": 61,
        "raw_energy": -58.852151623682204,
        "energy_change": -0.0007402596242087611,
        "converged": false,
        "core_set_size_after": 53,
        "iteration_time": 0.008819615,
        "cumulative_time": 0.601841973
      },
      {
        "iteration": 44,
        "core_set_size_before": 53,
        "target_pool_size": 1060,
        "actual_pool_size": 1135,
        "final_threshold": 0.005003154509899972,
        "pool_building_time": 0.005516683,
        "trim_m": 10,
        "trim_k": 1,
        "raw_dets_count": 63,
        "raw_energy": -58.85246482359162,
        "energy_change": -0.00031319990941369724,
        "converged": false,
        "core_set_size_after": 55,
        "iteration_time": 0.011736356,
        "cumulative_time": 0.613633329
      },
      {
        "iteration": 45,
        "core_set_size_before": 55,
        "target_pool_size": 1100,
        "actual_pool_size": 1112,
        "final_threshold": 0.005003154509899972,
        "pool_building_time": 0.007186115,
        "trim_m": 10,
        "trim_k": 1,
        "raw_dets_count": 65,
        "raw_energy": -58.85288011067427,
        "energy_change": -0.0004152870826530375,
        "converged": false,
        "core_set_size_after": 57,
        "iteration_time": 0.052797424,
        "cumulative_time": 0.666476678
      },
      {
        "iteration": 46,
        "core_set_size_before": 57,
        "target_pool_size": 1140,
        "actual_pool_size": 1406,
        "final_threshold": 0.004502839058909975,
        "pool_building_time": 0.001640466,
        "trim_m": 10,
        "trim_k": 1,
        "raw_dets_count": 67,
        "raw_energy": -58.856930352898864,
        "energy_change": -0.004050242224593603,
        "converged": false,
        "core_set_size_after": 59,
        "iteration_time": 0.00707529,
        "cumulative_time": 0.673595693
      },
      {
        "iteration": 47,
        "core_set_size_before": 59,
        "target_pool_size": 1180,
        "actual_pool_size": 1483,
        "final_threshold": 0.004502839058909975,
        "pool_building_time": 0.001654766,
        "trim_m": 10,
        "trim_k": 1,
        "raw_dets_count": 69,
        "raw_energy": -58.85709468725548,
        "energy_change": -0.00016433435661866724,
        "converged": false,
        "core_set_size_after": 61,
        "iteration_time": 0.031859752,
        "cumulative_time": 0.705504762
      },
      {
        "iteration": 48,
        "core_set_size_before": 61,
        "target_pool_size": 1220,
        "actual_pool_size": 1429,
        "final_threshold": 0.004502839058909975,
        "pool_building_time": 0.001981375,
        "trim_m": 10,
        "trim_k": 1,
        "raw_dets_count": 71,
        "raw_energy": -58.85720197113535,
        "energy_change": -0.00010728387987057886,
        "converged": false,
        "core_set_size_after": 63,
        "iteration_time": 0.044640925,
        "cumulative_time": 0.750189412
      },
      {
        "iteration": 49,
        "core_set_size_before": 63,
        "target_pool_size": 1260,
        "actual_pool_size": 1407,
        "final_threshold": 0.004502839058909975,
        "pool_building_time": 0.005194382,
        "trim_m": 10,
        "trim_k": 1,
        "raw_dets_count": 73,
        "raw_energy": -58.860353213204164,
        "energy_change": -0.003151242068810234,
        "converged": false,
        "core_set_size_after": 65,
        "iteration_time": 0.017547563,
        "cumulative_time": 0.767781709
      },
      {
        "iteration": 50,
        "core_set_size_before": 65,
        "target_pool_size": 1300,
        "actual_pool_size": 1350,
        "final_threshold": 0.004502839058909975,
        "pool_building_time": 0.005461682,
        "trim_m": 10,
        "trim_k": 1,
        "raw_dets_count": 75,
        "raw_energy": -58.86063748433792,
        "energy_change": -0.00028427113375784074,
        "converged": false,
        "core_set_size_after": 67,
        "iteration_time": 0.028293095,
        "cumulative_time": 0.796120546
      },
      {
        "iteration": 51,
        "core_set_size_before": 67,
        "target_pool_size": 1340,
        "actual_pool_size": 1693,
        "final_threshold": 0.004052555153018977,
        "pool_building_time": 0.003455466,
        "trim_m": 10,
        "trim_k": 1,
        "raw_dets_count": 77,
        "raw_energy": -58.860907899477084,
        "energy_change": -0.0002704151391625942,
        "converged": false,
        "core_set_size_after": 69,
        "iteration_time": 0.009847748,
        "cumulative_time": 0.805973977
      },
      {
        "iteration": 52,
        "core_set_size_before": 69,
        "target_pool_size": 1380,
        "actual_pool_size": 2015,
        "final_threshold": 0.004052555153018977,
        "pool_building_time": 0.002554016,
        "trim_m": 10,
        "trim_k": 1,
        "raw_dets_count": 79,
        "raw_energy": -58.86082986442364,
        "energy_change": 7.803505344128325e-05,
        "converged": false,
        "core_set_size_after": 71,
        "iteration_time": 0.044477942,
        "cumulative_time": 0.850496836
      },
      {
        "iteration": 53,
        "core_set_size_before": 71,
        "target_pool_size": 1420,
        "actual_pool_size": 1943,
        "final_threshold": 0.004052555153018977,
        "pool_building_time": 0.001899608,
        "trim_m": 10,
        "trim_k": 1,
        "raw_dets_count": 81,
        "raw_energy": -58.861639729145836,
        "energy_change": -0.000809864722192799,
        "converged": false,
        "core_set_size_after": 73,
        "iteration_time": 0.013844506,
        "cumulative_time": 0.864386625
      },
      {
        "iteration": 54,
        "core_set_size_before": 73,
        "target_pool_size": 1460,
        "actual_pool_size": 1929,
        "final_threshold": 0.004052555153018977,
        "pool_building_time": 0.005318957,
        "trim_m": 10,
        "trim_k": 1,
        "raw_dets_count": 83,
        "raw_energy": -58.86258187822511,
        "energy_change": -0.0009421490792718146,
        "converged": false,
        "core_set_size_after": 75,
        "iteration_time": 0.027129204,
        "cumulative_time": 0.891551395
      },
      {
        "iteration": 55,
        "core_set_size_before": 75,
        "target_pool_size": 1500,
        "actual_pool_size": 1816,
        "final_threshold": 0.004052555153018977,
        "pool_building_time": 0.001782367,
        "trim_m": 10,
        "trim_k": 1,
        "raw_dets_count": 85,
        "raw_energy": -58.86329101310033,
        "energy_change": -0.0007091348752226168,
        "converged": false,
        "core_set_size_after": 77,
        "iteration_time": 0.023676304,
        "cumulative_time": 0.91523439
      },
      {
        "iteration": 56,
        "core_set_size_before": 77,
        "target_pool_size": 1540,
        "actual_pool_size": 1734,
        "final_threshold": 0.004052555153018977,
        "pool_building_time": 0.009285648,
        "trim_m": 10,
        "trim_k": 1,
        "raw_dets_count": 87,
        "raw_energy": -58.86328453363957,
        "energy_change": 6.479460758157529e-06,
        "converged": false,
        "core_set_size_after": 79,
        "iteration_time": 0.036732843,
        "cumulative_time": 0.952005825
      },
      {
        "iteration": 57,
        "core_set_size_before": 79,
        "target_pool_size": 1580,
        "actual_pool_size": 1717,
        "final_threshold": 0.004052555153018977,
        "pool_building_time": 0.002047741,
        "trim_m": 10,
        "trim_k": 1,
        "raw_dets_count": 89,
        "raw_energy": -58.86355048533913,
        "energy_change": -0.00026595169956067366,
        "converged": false,
        "core_set_size_after": 81,
        "iteration_time": 0.012066631,
        "cumulative_time": 0.964105731
      },
      {
        "iteration": 58,
        "core_set_size_before": 81,
        "target_pool_size": 1620,
        "actual_pool_size": 1778,
        "final_threshold": 0.004052555153018977,
        "pool_building_time": 0.001961208,
        "trim_m": 10,
        "trim_k": 1,
        "raw_dets_count": 91,
        "raw_energy": -58.864092949707754,
        "energy_change": -0.0005424643686211539,
        "converged": false,
        "core_set_size_after": 83,
        "iteration_time": 0.028668562,
        "cumulative_time": 0.992814168
      },
      {
        "iteration": 59,
        "core_set_size_before": 83,
        "target_pool_size": 1660,
        "actual_pool_size": 1752,
        "final_threshold": 0.004052555153018977,
        "pool_building_time": 0.001808583,
        "trim_m": 10,
        "trim_k": 1,
        "raw_dets_count": 93,
        "raw_energy": -58.86411394595894,
        "energy_change": -2.0996251187455073e-05,
        "converged": false,
        "core_set_size_after": 85,
        "iteration_time": 0.017687171,
        "cumulative_time": 1.010546714
      },
      {
        "iteration": 60,
        "core_set_size_before": 85,
        "target_pool_size": 1700,
        "actual_pool_size": 2013,
        "final_threshold": 0.0036472996377170793,
        "pool_building_time": 0.020502805,
        "trim_m": 10,
        "trim_k": 1,
        "raw_dets_count": 95,
        "raw_energy": -58.86449619063716,
        "energy_change": -0.0003822446782208999,
        "converged": false,
        "core_set_size_after": 87,
        "iteration_time": 0.048515216,
        "cumulative_time": 1.059102264
      },
      {
        "iteration": 61,
        "core_set_size_before": 87,
        "target_pool_size": 1740,
        "actual_pool_size": 2413,
        "final_threshold": 0.0036472996377170793,
        "pool_building_time": 0.002173141,
        "trim_m": 10,
        "trim_k": 1,
        "raw_dets_count": 97,
        "raw_energy": -58.86455480953905,
        "energy_change": -5.861890188896268e-05,
        "converged": false,
        "core_set_size_after": 89,
        "iteration_time": 0.019542138,
        "cumulative_time": 1.078690694
      },
      {
        "iteration": 62,
        "core_set_size_before": 89,
        "target_pool_size": 1780,
        "actual_pool_size": 2293,
        "final_threshold": 0.0036472996377170793,
        "pool_building_time": 0.010597673,
        "trim_m": 10,
        "trim_k": 1,
        "raw_dets_count": 99,
        "raw_energy": -58.86471645669328,
        "energy_change": -0.00016164715422917197,
        "converged": false,
        "core_set_size_after": 91,
        "iteration_time": 0.049802582,
        "cumulative_time": 1.128537276
      },
      {
        "iteration": 63,
        "core_set_size_before": 91,
        "target_pool_size": 1820,
        "actual_pool_size": 2324,
        "final_threshold": 0.0036472996377170793,
        "pool_building_time": 0.002591783,
        "trim_m": 10,
        "trim_k": 1,
        "raw_dets_count": 101,
        "raw_energy": -58.864832062738564,
        "energy_change": -0.00011560604528426666,
        "converged": false,
        "core_set_size_after": 93,
        "iteration_time": 0.029887544,
        "cumulative_time": 1.158466987
      },
      {
        "iteration": 64,
        "core_set_size_before": 93,
        "target_pool_size": 1860,
        "actual_pool_size": 2203,
        "final_threshold": 0.0036472996377170793,
        "pool_building_time": 0.002109341,
        "trim_m": 10,
        "trim_k": 1,
        "raw_dets_count": 103,
        "raw_energy": -58.86483836440357,
        "energy_change": -6.301665003149992e-06,
        "converged": false,
        "core_set_size_after": 95,
        "iteration_time": 0.030855178,
        "cumulative_time": 1.189362315
      },
      {
        "iteration": 65,
        "core_set_size_before": 95,
        "target_pool_size": 1900,
        "actual_pool_size": 2229,
        "final_threshold": 0.0036472996377170793,
        "pool_building_time": 0.017421064,
        "trim_m": 10,
        "trim_k": 1,
        "raw_dets_count": 105,
        "raw_energy": -58.864990421768724,
        "energy_change": -0.0001520573651561108,
        "converged": false,
        "core_set_size_after": 97,
        "iteration_time": 0.078455378,
        "cumulative_time": 1.267854726
      },
      {
        "iteration": 66,
        "core_set_size_before": 97,
        "target_pool_size": 1940,
        "actual_pool_size": 2146,
        "final_threshold": 0.0036472996377170793,
        "pool_building_time": 0.002067816,
        "trim_m": 10,
        "trim_k": 1,
        "raw_dets_count": 107,
        "raw_energy": -58.86556517680541,
        "energy_change": -0.0005747550366876908,
        "converged": false,
        "core_set_size_after": 99,
        "iteration_time": 0.034434761,
        "cumulative_time": 1.302330553
      },
      {
        "iteration": 67,
        "core_set_size_before": 99,
        "target_pool_size": 1980,
        "actual_pool_size": 2215,
        "final_threshold": 0.0036472996377170793,
        "pool_building_time": 0.00821709,
        "trim_m": 10,
        "trim_k": 1,
        "raw_dets_count": 109,
        "raw_energy": -58.86578540442238,
        "energy_change": -0.0002202276169711581,
        "converged": false,
        "core_set_size_after": 101,
        "iteration_time": 0.025729361,
        "cumulative_time": 1.328094014
      },
      {
        "iteration": 68,
        "core_set_size_before": 101,
        "target_pool_size": 2020,
        "actual_pool_size": 2149,
        "final_threshold": 0.0036472996377170793,
        "pool_building_time": 0.002157191,
        "trim_m": 10,
        "trim_k": 2,
        "raw_dets_count": 121,
        "raw_energy": -58.86603208104984,
        "energy_change": -0.0002466766274551446,
        "converged": false,
        "core_set_size_after": 104,
        "iteration_time": 0.01090164,
        "cumulative_time": 1.339027554
      },
      {
        "iteration": 69,
        "core_set_size_before": 104,
        "target_pool_size": 2080,
        "actual_pool_size": 2083,
        "final_threshold": 0.0036472996377170793,
        "pool_building_time": 0.002481967,
        "trim_m": 10,
        "trim_k": 2,
        "raw_dets_count": 124,
        "raw_energy": -58.86721708184572,
        "energy_change": -0.0011850007958855713,
        "converged": false,
        "core_set_size_after": 107,
        "iteration_time": 0.022062329,
        "cumulative_time": 1.361096208
      },
      {
        "iteration": 70,
        "core_set_size_before": 107,
        "target_pool_size": 2140,
        "actual_pool_size": 2382,
        "final_threshold": 0.002658881435895751,
        "pool_building_time": 0.007626298,
        "trim_m": 10,
        "trim_k": 2,
        "raw_dets_count": 127,
        "raw_energy": -58.86735792848894,
        "energy_change": -0.00014084664321956097,
        "converged": false,
        "core_set_size_after": 110,
        "iteration_time": 0.050058516,
        "cumulative_time": 1.411195424
      },
      {
        "iteration": 71,
        "core_set_size_before": 110,
        "target_pool_size": 2200,
        "actual_pool_size": 3782,
        "final_threshold": 0.002658881435895751,
        "pool_building_time": 0.003686558,
        "trim_m": 10,
        "trim_k": 2,
        "raw_dets_count": 130,
        "raw_energy": -58.87205109967225,
        "energy_change": -0.004693171183305367,
        "converged": false,
        "core_set_size_after": 113,
        "iteration_time": 0.02405342,
        "cumulative_time": 1.435306686
      },
      {
        "iteration": 72,
        "core_set_size_before": 113,
        "target_pool_size": 2260,
        "actual_pool_size": 3973,
        "final_threshold": 0.002658881435895751,
        "pool_building_time": 0.006250565,
        "trim_m": 10,
        "trim_k": 2,
        "raw_dets_count": 133,
        "raw_energy": -58.87256771133148,
        "energy_change": -0.0005166116592292269,
        "converged": false,
        "core_set_size_after": 116,
        "iteration_time": 0.041897159,
        "cumulative_time": 1.477243904
      },
      {
        "iteration": 73,
        "core_set_size_before": 116,
        "target_pool_size": 2320,
        "actual_pool_size": 3845,
        "final_threshold": 0.002658881435895751,
        "pool_building_time": 0.016359197,
        "trim_m": 10,
        "trim_k": 2,
        "raw_dets_count": 136,
        "raw_energy": -58.87270871735734,
        "energy_change": -0.00014100602586353261,
        "converged": false,
        "core_set_size_after": 119,
        "iteration_time": 0.037162301,
        "cumulative_time": 1.514448555
      },
      {
        "iteration": 74,
        "core_set_size_before": 119,
        "target_pool_size": 2380,
        "actual_pool_size": 3830,
        "final_threshold": 0.002658881435895751,
        "pool_building_time": 0.007608699,
        "trim_m": 10,
        "trim_k": 2,
        "raw_dets_count": 139,
        "raw_energy": -58.87272424791891,
        "energy_change": -1.553056156922139e-05,
        "converged": false,
        "core_set_size_after": 122,
        "iteration_time": 0.029088852,
        "cumulative_time": 1.543590116
      },
      {
        "iteration": 75,
        "core_set_size_before": 122,
        "target_pool_size": 2440,
        "actual_pool_size": 3556,
        "final_threshold": 0.002658881435895751,
        "pool_building_time": 0.003509458,
        "trim_m": 10,
        "trim_k": 2,
        "raw_dets_count": 142,
        "raw_energy": -58.872892841252096,
        "energy_change": -0.0001685933331856404,
        "converged": false,
        "core_set_size_after": 125,
        "iteration_time": 0.057201731,
        "cumulative_time": 1.600827139
      },
      {
        "iteration": 76,
        "core_set_size_before": 125,
        "target_pool_size": 2500,
        "actual_pool_size": 3612,
        "final_threshold": 0.002658881435895751,
        "pool_building_time": 0.006729341,
        "trim_m": 10,
        "trim_k": 2,
        "raw_dets_count": 145,
        "raw_energy": -58.873012809360795,
        "energy_change": -0.00011996810869874253,
        "converged": false,
        "core_set_size_after": 128,
        "iteration_time": 0.037481026,
        "cumulative_time": 1.638315774
      },
      {
        "iteration": 77,
        "core_set_size_before": 128,
        "target_pool_size": 2560,
        "actual_pool_size": 3385,
        "final_threshold": 0.002658881435895751,
        "pool_building_time": 0.003991075,
        "trim_m": 10,
        "trim_k": 2,
        "raw_dets_count": 148,
        "raw_energy": -58.873412338200936,
        "energy_change": -0.0003995288401412722,
        "converged": false,
        "core_set_size_after": 131,
        "iteration_time": 0.033546419,
        "cumulative_time": 1.67186861
      },
      {
        "iteration": 78,
        "core_set_size_before": 131,
        "target_pool_size": 2620,
        "actual_pool_size": 3565,
        "final_threshold": 0.002658881435895751,
        "pool_building_time": 0.008334424,
        "trim_m": 10,
        "trim_k": 2,
        "raw_dets_count": 151,
        "raw_energy": -58.87488875084437,
        "energy_change": -0.0014764126434343439,
        "converged": false,
        "core_set_size_after": 134,
        "iteration_time": 0.033421935,
        "cumulative_time": 1.70532437
      },
      {
        "iteration": 79,
        "core_set_size_before": 134,
        "target_pool_size": 2680,
        "actual_pool_size": 3568,
        "final_threshold": 0.002658881435895751,
        "pool_building_time": 0.005192458,
        "trim_m": 10,
        "trim_k": 2,
        "raw_dets_count": 154,
        "raw_energy": -58.87525043676988,
        "energy_change": -0.0003616859255117788,
        "converged": false,
        "core_set_size_after": 137,
        "iteration_time": 0.025267362,
        "cumulative_time": 1.73066149
      },
      {
        "iteration": 80,
        "core_set_size_before": 137,
        "target_pool_size": 2740,
        "actual_pool_size": 3710,
        "final_threshold": 0.002658881435895751,
        "pool_building_time": 0.009667715,
        "trim_m": 10,
        "trim_k": 2,
        "raw_dets_count": 157,
        "raw_energy": -58.87544594014846,
        "energy_change": -0.00019550337857765498,
        "converged": false,
        "core_set_size_after": 140,
        "iteration_time": 0.05043554,
        "cumulative_time": 1.781131314
      },
      {
        "iteration": 81,
        "core_set_size_before": 140,
        "target_pool_size": 2800,
        "actual_pool_size": 3550,
        "final_threshold": 0.002658881435895751,
        "pool_building_time": 0.006478174,
        "trim_m": 10,
        "trim_k": 2,
        "raw_dets_count": 160,
        "raw_energy": -58.87581681492235,
        "energy_change": -0.0003708747738926377,
        "converged": false,
        "core_set_size_after": 143,
        "iteration_time": 0.031726836,
        "cumulative_time": 1.812893809
      },
      {
        "iteration": 82,
        "core_set_size_before": 143,
        "target_pool_size": 2860,
        "actual_pool_size": 3459,
        "final_threshold": 0.002658881435895751,
        "pool_building_time": 0.004420624,
        "trim_m": 10,
        "trim_k": 2,
        "raw_dets_count": 163,
        "raw_energy": -58.87586654324873,
        "energy_change": -4.972832638117097e-05,
        "converged": false,
        "core_set_size_after": 146,
        "iteration_time": 0.04858195,
        "cumulative_time": 1.8614841
      },
      {
        "iteration": 83,
        "core_set_size_before": 146,
        "target_pool_size": 2920,
        "actual_pool_size": 3395,
        "final_threshold": 0.002658881435895751,
        "pool_building_time": 0.003738074,
        "trim_m": 10,
        "trim_k": 2,
        "raw_dets_count": 166,
        "raw_energy": -58.87693141435119,
        "energy_change": -0.0010648711024572322,
        "converged": false,
        "core_set_size_after": 149,
        "iteration_time": 0.022154912,
        "cumulative_time": 1.883646712
      },
      {
        "iteration": 84,
        "core_set_size_before": 149,
        "target_pool_size": 2980,
        "actual_pool_size": 3769,
        "final_threshold": 0.002658881435895751,
        "pool_building_time": 0.003784549,
        "trim_m": 10,
        "trim_k": 2,
        "raw_dets_count": 169,
        "raw_energy": -58.8768933533157,
        "energy_change": 3.806103548953388e-05,
        "converged": false,
        "core_set_size_after": 152,
        "iteration_time": 0.040161726,
        "cumulative_time": 1.923815405
      },
      {
        "iteration": 85,
        "core_set_size_before": 152,
        "target_pool_size": 3040,
        "actual_pool_size": 3704,
        "final_threshold": 0.002658881435895751,
        "pool_building_time": 0.004111066,
        "trim_m": 10,
        "trim_k": 2,
        "raw_dets_count": 172,
        "raw_energy": -58.8775150150116,
        "energy_change": -0.0006216616959022758,
        "converged": false,
        "core_set_size_after": 156,
        "iteration_time": 0.05343854,
        "cumulative_time": 1.977313162
      },
      {
        "iteration": 86,
        "core_set_size_before": 156,
        "target_pool_size": 3120,
        "actual_pool_size": 3655,
        "final_threshold": 0.002658881435895751,
        "pool_building_time": 0.003705166,
        "trim_m": 10,
        "trim_k": 2,
        "raw_dets_count": 176,
        "raw_energy": -58.87795634780695,
        "energy_change": -0.0004413327953471935,
        "converged": false,
        "core_set_size_after": 160,
        "iteration_time": 0.028605861,
        "cumulative_time": 2.005959906
      },
      {
        "iteration": 87,
        "core_set_size_before": 160,
        "target_pool_size": 3200,
        "actual_pool_size": 3513,
        "final_threshold": 0.002658881435895751,
        "pool_building_time": 0.008433974,
        "trim_m": 10,
        "trim_k": 2,
        "raw_dets_count": 180,
        "raw_energy": -58.878088115253966,
        "energy_change": -0.0001317674470158181,
        "converged": false,
        "core_set_size_after": 164,
        "iteration_time": 0.065507004,
        "cumulative_time": 2.071522369
      },
      {
        "iteration": 88,
        "core_set_size_before": 164,
        "target_pool_size": 3280,
        "actual_pool_size": 3443,
        "final_threshold": 0.002658881435895751,
        "pool_building_time": 0.008312424,
        "trim_m": 10,
        "trim_k": 2,
        "raw_dets_count": 184,
        "raw_energy": -58.87816575471111,
        "energy_change": -7.763945714600595e-05,
        "converged": false,
        "core_set_size_after": 168,
        "iteration_time": 0.048543358,
        "cumulative_time": 2.120107252
      },
      {
        "iteration": 89,
        "core_set_size_before": 168,
        "target_pool_size": 3360,
        "actual_pool_size": 3452,
        "final_threshold": 0.002658881435895751,
        "pool_building_time": 0.015691864,
        "trim_m": 10,
        "trim_k": 2,
        "raw_dets_count": 188,
        "raw_energy": -58.87861615777726,
        "energy_change": -0.0004504030661465208,
        "converged": false,
        "core_set_size_after": 172,
        "iteration_time": 0.042683384,
        "cumulative_time": 2.162835553
      },
      {
        "iteration": 90,
        "core_set_size_before": 172,
        "target_pool_size": 3440,
        "actual_pool_size": 3474,
        "final_threshold": 0.002392993292306176,
        "pool_building_time": 0.013005481,
        "trim_m": 10,
        "trim_k": 2,
        "raw_dets_count": 192,
        "raw_energy": -58.87904619632248,
        "energy_change": -0.0004300385452182809,
        "converged": false,
        "core_set_size_after": 176,
        "iteration_time": 0.043335867,
        "cumulative_time": 2.20617857
      },
      {
        "iteration": 91,
        "core_set_size_before": 176,
        "target_pool_size": 3520,
        "actual_pool_size": 4202,
        "final_threshold": 0.002392993292306176,
        "pool_building_time": 0.007887457,
        "trim_m": 10,
        "trim_k": 2,
        "raw_dets_count": 196,
        "raw_energy": -58.879067210579315,
        "energy_change": -2.101425683775915e-05,
        "converged": false,
        "core_set_size_after": 180,
        "iteration_time": 0.058673714,
        "cumulative_time": 2.264860259
      },
      {
        "iteration": 92,
        "core_set_size_before": 180,
        "target_pool_size": 3600,
        "actual_pool_size": 4227,
        "final_threshold": 0.002392993292306176,
        "pool_building_time": 0.005141216,
        "trim_m": 10,
        "trim_k": 2,
        "raw_dets_count": 200,
        "raw_energy": -58.879149856173356,
        "energy_change": -8.264559404125293e-05,
        "converged": false,
        "core_set_size_after": 184,
        "iteration_time": 0.0422146,
        "cumulative_time": 2.307081459
      },
      {
        "iteration": 93,
        "core_set_size_before": 184,
        "target_pool_size": 3680,
        "actual_pool_size": 4048,
        "final_threshold": 0.002392993292306176,
        "pool_building_time": 0.015331889,
        "trim_m": 10,
        "trim_k": 2,
        "raw_dets_count": 204,
        "raw_energy": -58.87930947004776,
        "energy_change": -0.00015961387440199815,
        "converged": false,
        "core_set_size_after": 188,
        "iteration_time": 0.049154041,
        "cumulative_time": 2.356243934
      },
      {
        "iteration": 94,
        "core_set_size_before": 188,
        "target_pool_size": 3760,
        "actual_pool_size": 4123,
        "final_threshold": 0.002392993292306176,
        "pool_building_time": 0.009415723,
        "trim_m": 10,
        "trim_k": 2,
        "raw_dets_count": 208,
        "raw_energy": -58.87934412201851,
        "energy_change": -3.465197075058768e-05,
        "converged": false,
        "core_set_size_after": 192,
        "iteration_time": 0.04749295,
        "cumulative_time": 2.4037433
      },
      {
        "iteration": 95,
        "core_set_size_before": 192,
        "target_pool_size": 3840,
        "actual_pool_size": 4024,
        "final_threshold": 0.002392993292306176,
        "pool_building_time": 0.014128397,
        "trim_m": 10,
        "trim_k": 2,
        "raw_dets_count": 212,
        "raw_energy": -58.879408134288475,
        "energy_change": -6.401226996644027e-05,
        "converged": false,
        "core_set_size_after": 196,
        "iteration_time": 0.047524116,
        "cumulative_time": 2.451274383
      },
      {
        "iteration": 96,
        "core_set_size_before": 196,
        "target_pool_size": 3920,
        "actual_pool_size": 4070,
        "final_threshold": 0.002392993292306176,
        "pool_building_time": 0.006998749,
        "trim_m": 10,
        "trim_k": 2,
        "raw_dets_count": 216,
        "raw_energy": -58.87948936285963,
        "energy_change": -8.122857115466786e-05,
        "converged": false,
        "core_set_size_after": 200,
        "iteration_time": 0.07883396,
        "cumulative_time": 2.530115493
      }
    ],
    "total_time": 2.538428742,
    "final_energy": -58.87946474724951,
    "final_core_energy": -58.87946474724951,
    "final_core_dets_count": 200,
    "final_raw_energy": -58.87946474724951,
    "final_raw_dets_count": 200,
    "final_electronic_energy": -58.87946474724951,
    "final_dets_count": 200,
    "converged": false,
    "total_iterations": 96,
    "n_electrons": 22,
    "n_orbitals": 15,
    "nuclear_repulsion": 0.0,
    "results_dir": "trimci_single_run_results/FCIDUMP_22e_15o_20260414_205211000243_8"
  },
  "top_10_determinants": [
    [
      -0.4112464138858899,
      "0 1 4 5 6 7 9 10 12 13 14 , 1 2 3 4 5 6 7 8 9 10 11"
    ],
    [
      -0.40259784007363836,
      "0 1 4 5 6 7 8 9 10 13 14 , 1 2 3 4 5 6 7 9 10 11 12"
    ],
    [
      0.40090950759996213,
      "0 1 4 5 6 7 8 9 10 12 14 , 1 2 3 4 5 6 7 9 10 11 13"
    ],
    [
      -0.3716429381779504,
      "0 1 4 5 6 7 8 9 10 12 13 , 1 2 3 4 5 6 7 9 10 11 14"
    ],
    [
      -0.19340168793998572,
      "0 1 3 5 6 7 8 9 10 12 14 , 1 2 3 4 5 6 7 9 10 11 13"
    ],
    [
      0.19189782159183555,
      "0 1 3 5 6 7 8 9 10 13 14 , 1 2 3 4 5 6 7 9 10 11 12"
    ],
    [
      0.18884343573926746,
      "0 1 3 5 6 7 9 10 12 13 14 , 1 2 3 4 5 6 7 8 9 10 11"
    ],
    [
      0.17347190759925987,
      "0 1 3 5 6 7 8 9 10 12 13 , 1 2 3 4 5 6 7 9 10 11 14"
    ],
    [
      -0.16870425348057025,
      "0 1 3 4 5 7 8 9 10 13 14 , 1 2 3 4 5 6 7 9 10 11 12"
    ],
    [
      0.16850845980869814,
      "0 1 3 4 5 7 8 9 10 12 14 , 1 2 3 4 5 6 7 9 10 11 13"
    ]
  ]
}